ipfs_car_decoder/__init__.py
ipfs_car_decoder/async_stream.py
ipfs_car_decoder/decoder.py
ipfs_car_decoder/py.typed
ipfs_car_decoder-0.1.1.dist-info/METADATA
ipfs_car_decoder-0.1.1.dist-info/WHEEL
ipfs_car_decoder-0.1.1.dist-info/top_level.txt
ipfs_car_decoder-0.1.1.dist-info/RECORD
