Metadata-Version: 2.1
Name: ipfs-car-decoder
Version: 0.1.1
Summary: Pure python implementation of a ipfs CAR block decoder.
Home-page: https://github.com/kralverde/py-ipfs-car-decoder/
Author: kralverde
Project-URL: Bug Tracker, https://github.com/kralverde/py-ipfs-car-decoder/issues
Classifier: Development Status :: 3 - Alpha
Classifier: Programming Language :: Python :: 3.11
Classifier: Programming Language :: Python :: 3.10
Classifier: Programming Language :: Python :: 3.9
Classifier: Programming Language :: Python :: 3.8
Classifier: Programming Language :: Python :: 3.7
Classifier: Operating System :: OS Independent
Classifier: Natural Language :: English
Classifier: Typing :: Typed
Requires-Python: >=3.7
Requires-Dist: aiofiles
Requires-Dist: attrs
Requires-Dist: dag-cbor
Requires-Dist: unix-fs-exporter >=0.2.0
Requires-Dist: multiformats
Provides-Extra: dev
Requires-Dist: types-aiofiles ; extra == 'dev'
